aibrix/__init__.py
aibrix/__version__.py
aibrix/app.py
aibrix/batch/README.md
aibrix/batch/__init__.py
aibrix/batch/constant.py
aibrix/batch/driver.py
aibrix/batch/job_driver.py
aibrix/batch/job_entity/__init__.py
aibrix/batch/job_entity/batch_job.py
aibrix/batch/job_entity/job_entity_manager.py
aibrix/batch/job_entity/k8s_transformer.py
aibrix/batch/job_manager.py
aibrix/batch/job_progress_manager.py
aibrix/batch/scheduler.py
aibrix/batch/storage/__init__.py
aibrix/batch/storage/adapter.py
aibrix/batch/storage/batch_metastore.py
aibrix/batch/storage/batch_storage.py
aibrix/batch/worker.py
aibrix/common/__init__.py
aibrix/common/errors.py
aibrix/config.py
aibrix/downloader/__init__.py
aibrix/downloader/__main__.py
aibrix/downloader/base.py
aibrix/downloader/entity.py
aibrix/downloader/huggingface.py
aibrix/downloader/s3.py
aibrix/downloader/tos.py
aibrix/downloader/utils.py
aibrix/envs.py
aibrix/gpu_optimizer/Makefile
aibrix/gpu_optimizer/README.md
aibrix/gpu_optimizer/__init__.py
aibrix/gpu_optimizer/app.py
aibrix/gpu_optimizer/load_monitor/__init__.py
aibrix/gpu_optimizer/load_monitor/clusterer.py
aibrix/gpu_optimizer/load_monitor/helpers.py
aibrix/gpu_optimizer/load_monitor/load_reader.py
aibrix/gpu_optimizer/load_monitor/monitor.py
aibrix/gpu_optimizer/load_monitor/profile_reader.py
aibrix/gpu_optimizer/load_monitor/visualizer.py
aibrix/gpu_optimizer/optimizer/__init__.py
aibrix/gpu_optimizer/optimizer/optimizer.py
aibrix/gpu_optimizer/optimizer/profiling/README.md
aibrix/gpu_optimizer/optimizer/profiling/benchmark.py
aibrix/gpu_optimizer/optimizer/profiling/benchmark.sh
aibrix/gpu_optimizer/optimizer/profiling/gen_benchmark_prompt.py
aibrix/gpu_optimizer/optimizer/profiling/gen_profile.py
aibrix/gpu_optimizer/optimizer/profiling/gpu_benchmark.py
aibrix/gpu_optimizer/optimizer/profiling/result/simulator-llama2-7b-a100.json
aibrix/gpu_optimizer/optimizer/profiling/result/simulator-llama2-7b-a100.jsonl
aibrix-0.5.0.dist-info/METADATA
aibrix-0.5.0.dist-info/WHEEL
aibrix-0.5.0.dist-info/entry_points.txt
aibrix-0.5.0.dist-info/RECORD
