Metadata-Version: 2.4
Name: aibrix
Version: 0.5.0
Summary: AIBrix, the foundational building blocks for constructing your own GenAI inference infrastructure.
License: Apache-2.0
Author: AIBrix Authors
Author-email: brosoul@126.com
Requires-Python: >=3.10,<3.13
Classifier: Intended Audience :: Developers
Classifier: Intended Audience :: Education
Classifier: Intended Audience :: Science/Research
Classifier: License :: OSI Approved :: Apache Software License
Classifier: Operating System :: OS Independent
Classifier: Programming Language :: Python :: 3
Classifier: Programming Language :: Python :: 3.10
Classifier: Programming Language :: Python :: 3.11
Classifier: Programming Language :: Python :: 3.12
Classifier: Topic :: Scientific/Engineering
Classifier: Topic :: Scientific/Engineering :: Artificial Intelligence
Classifier: Topic :: Software Development
Classifier: Topic :: Software Development :: Libraries
Classifier: Topic :: Software Development :: Libraries :: Python Modules
Requires-Dist: PyYAML (>=6.0.1,<7.0.0)
Requires-Dist: aiohttp (>=3.11.7,<4.0.0)
Requires-Dist: boto3 (>=1.35.5,<2.0.0)
Requires-Dist: dash (>=2.18.2,<3.0.0)
Requires-Dist: fastapi (>=0.112.2,<0.113.0)
Requires-Dist: filelock (>=3.16.1,<4.0.0)
Requires-Dist: google-cloud-storage (>=2.10.0,<3.0.0)
Requires-Dist: gunicorn (>=23.0.0,<24.0.0)
Requires-Dist: hf-transfer (>=0.1.8,<0.2.0)
Requires-Dist: httpx (>=0.27.2,<0.28.0)
Requires-Dist: huggingface-hub (>=0.24.6,<0.25.0)
Requires-Dist: incdbscan (>=0.1.0,<0.2.0)
Requires-Dist: kopf[uvloop] (>=1.37.2,<2.0.0)
Requires-Dist: kubernetes (>=31.0.0,<32.0.0)
Requires-Dist: matplotlib (>=3.9.2,<4.0.0)
Requires-Dist: numpy (==1.26.4)
Requires-Dist: pandas (>=2.2.3,<3.0.0)
Requires-Dist: prometheus-client (>=0.20.0,<0.21.0)
Requires-Dist: pulp (==2.8.0)
Requires-Dist: pydantic-settings (>=2.6.1,<3.0.0)
Requires-Dist: python-multipart (>=0.0.20,<0.0.21)
Requires-Dist: redis (>=5.2.0,<6.0.0)
Requires-Dist: structlog (>=24.4.0,<25.0.0)
Requires-Dist: tenacity (>=9.0.0,<10.0.0)
Requires-Dist: tos (==2.8.0)
Requires-Dist: types-PyYAML (>=6.0.12.20240917,<7.0.0.0)
Requires-Dist: types-redis (>=4.6.0.20241004,<5.0.0.0)
Requires-Dist: types-requests (>=2.31.0,<3.0.0)
Requires-Dist: uvicorn (>=0.30.6,<0.31.0)
Project-URL: Repository, https://github.com/vllm-project/aibrix/tree/main/python/aibrix
